{
    "id": "66ce07e7fba249e26d0c0b56",
    "title": "بيت لحم هذا العام من دون احتفالات",
    "full_text": "\nمهد السيد المسيح من دون احتفالات حزناً على غزة\n 11 كانون الأول 2023 \nشبكة الميادين الإعلامية قناة فضائية عربية إخبارية مستقلة انطلقت في الحادي عشر من حزيران من العام 2012\nواتخذت من العاصمة بيروت مقرا لها.\n جميع الحقوق محفوظة",
    "entities": [
        {
            "entity": "المسيح",
            "type": "PER"
        },
        {
            "entity": "غزة",
            "type": "LOC"
        },
        {
            "entity": "بيروت",
            "type": "LOC"
        }
    ]
}