{
    "id": "66ce07e6fba249e26d0c073c",
    "title": "بعدسة هاتف أو كاميرا.. أبطال من نوعٍ آخر في غزة",
    "full_text": "\nكبرنا وعرفنا أن الأبطال لا يلبسون دوماً رداء.. معتز عزايرة، صالح الجعفراوي وغيرهما، مناضلون من نوعٍ آخر في غزة\n 14 تشرين ثاني 2023 \nشبكة الميادين الإعلامية قناة فضائية عربية إخبارية مستقلة انطلقت في الحادي عشر من حزيران من العام 2012\nواتخذت من العاصمة بيروت مقرا لها.\n جميع الحقوق محفوظة",
    "entities": [
        {
            "entity": "معتز عزايرة",
            "type": "PER"
        },
        {
            "entity": "صالح الجعفراوي",
            "type": "PER"
        },
        {
            "entity": "غزة",
            "type": "LOC"
        },
        {
            "entity": "بيروت",
            "type": "LOC"
        }
    ]
}