{
    "id": "66ce07ebfba249e26d0c2939",
    "title": "أي دلالات لسرعة إعادة تشغيل ميناء الحديدة؟",
    "full_text": "\nكاميرا الميادين تجول في ميناء الحديدة وبين الدمار الذي خلفه العدوان الإسرائيلي. يؤكد وزير حقوق الإنسان أن العدوان أتى بعد تخطيط أميركي وأن المنظمات الأممية التي تُشرف على الميناء غائبة ولم تقم بالدور المطلوب منها.\n 23 تموز \nشبكة الميادين الإعلامية قناة فضائية عربية إخبارية مستقلة انطلقت في الحادي عشر من حزيران من العام 2012\nواتخذت من العاصمة بيروت مقرا لها.\n جميع الحقوق محفوظة",
    "entities": [
        {
            "entity": "ميناء الحديدة",
            "type": "LOC"
        },
        {
            "entity": "بيروت",
            "type": "LOC"
        }
    ]
}